{
  "validation_status": "PASS",
  "feedback": "The action_plan correctly identifies 'green soda can' as the primary target which matches the user intent to drink sprite (Sprite comes in a green can). The plan contains only one step: picking the object directly from its location, which is logically valid and safe given there are no obvious obstructions preventing immediate interaction.",
  "final_action_plan": [
    {
      "step": 2,
      "action": "pick",
      "target": "green soda can",
      "target_role": "primary_target",
      "step_intent": "pick_primary_target",
      "explanation": "Pick the green soda can"
    }
  ]
}